pgml-1.1.1.dist-info/METADATA
pgml-1.1.1.dist-info/WHEEL
pgml/__init__.py
pgml/pgml.pyi
pgml/__main__.py
pgml/pgml.cpython-310-aarch64-linux-gnu.so
pgml-1.1.1.dist-info/RECORD
