Metadata-Version: 2.3
Name: pgml
Version: 1.1.1
Classifier: Programming Language :: Rust
Classifier: Programming Language :: Python :: Implementation :: CPython
Classifier: Programming Language :: Python :: Implementation :: PyPy
Summary: Python SDK is designed to facilitate the development of scalable vector search applications on PostgreSQL databases.
Keywords: postgres,machine learning,vector databases,embeddings
Home-Page: https://postgresml.org/
Author: PosgresML <team@postgresml.org>
Author-email: PostgresML <team@postgresml.org>
License: MIT
Requires-Python: >=3.7
Project-URL: Homepage, https://postgresml.org
Project-URL: Repository, https://github.com/postgresml/postgresml
Project-URL: Documentation, https://github.com/postgresml/postgresml/tree/master/pgml-sdks/pgml/python/
